LICENSE
thejourneyplanner/__init__.py
thejourneyplanner/computation/__init__.py
thejourneyplanner/computation/route_planning.py
thejourneyplanner/config/__init__.py
thejourneyplanner/config/constants.py
thejourneyplanner/integrations/__init__.py
thejourneyplanner/integrations/geocoding.py
thejourneyplanner/integrations/google_maps.py
thejourneyplanner/interface/__init__.py
thejourneyplanner/interface/command_line.py
thejourneyplanner/logs/__init__.py
thejourneyplanner/logs/setup_logging.py
thejourneyplanner/main.py
thejourneyplanner/py.typed
thejourneyplanner/utilities/__init__.py
thejourneyplanner/utilities/file_interaction.py
thejourneyplanner/utilities/polyline_interaction.py
thejourneyplanner/utilities/unit_conversion.py
thejourneyplanner/VERSION
thejourneyplanner-0.4.1.dist-info/entry_points.txt
thejourneyplanner-0.4.1.dist-info/LICENSE
thejourneyplanner-0.4.1.dist-info/METADATA
thejourneyplanner-0.4.1.dist-info/WHEEL
thejourneyplanner-0.4.1.dist-info/RECORD
