Metadata-Version: 2.1
Name: thejourneyplanner
Version: 0.4.1
Summary: Plan a quick walk in the car!
Home-page: https://github.com/unkokaeru/thejourneyplanner
License: MIT
Author: W. Fayers
Author-email: wills@fayers.com
Requires-Python: >=3.8,<4.0
Classifier: License :: OSI Approved :: MIT License
Classifier: Programming Language :: Python :: 3
Classifier: Programming Language :: Python :: 3.8
Classifier: Programming Language :: Python :: 3.9
Classifier: Programming Language :: Python :: 3.10
Classifier: Programming Language :: Python :: 3.11
Classifier: Programming Language :: Python :: 3.12
Provides-Extra: dev
Provides-Extra: devlint
Provides-Extra: docs
Provides-Extra: lint
Provides-Extra: release
Provides-Extra: test
Provides-Extra: types
Requires-Dist: folium (>=0.12.1,<0.13.0)
Requires-Dist: geocoder (>=1.38.1,<2.0.0)
Requires-Dist: polyline (>=1.4.0,<2.0.0)
Requires-Dist: questionary (>=1.9.0,<2.0.0)
Requires-Dist: requests (>=2.25.1,<3.0.0)
Requires-Dist: rich (>=12.0.0,<13.0.0)
Project-URL: Repository, https://github.com/unkokaeru/thejourneyplanner
